Metadata-Version: 2.1
Name: lyyak
Version: 1.11
Summary: lyydata for lyy
Author: yy
Author-email: 
License: MIT
License-File: LICENSE
